SLTev/ASRev.py
SLTev/ASReval.py
SLTev/MTeval.py
SLTev/SLTev.py
SLTev/SLTeval.py
SLTev/__init__.py
SLTev/__main__.py
SLTev/delay_modules.py
SLTev/evaluator.py
SLTev/files_modules.py
SLTev/flicker_modules.py
SLTev/index_parser.py
SLTev/multi_docs_evaluator.py
SLTev/multi_docs_utils.py
SLTev/mwerSegmenter
SLTev/quality_modules.py
SLTev/utilities.py
SLTev-1.2.3.data/data/SLTev/mwerSegmenter
SLTev-1.2.3.dist-info/METADATA
SLTev-1.2.3.dist-info/WHEEL
SLTev-1.2.3.dist-info/entry_points.txt
SLTev-1.2.3.dist-info/top_level.txt
SLTev-1.2.3.dist-info/RECORD
