Metadata-Version: 2.1
Name: SLTev
Version: 1.2.3
Summary: a tool for evaluation
Home-page: https://github.com/ELITR/SLTev.git
Author: Mohammad Mahmoudi
Author-email: zaribar2928@gmail.com
License: MIT
Platform: UNKNOWN
Classifier: Programming Language :: Python :: 3.6
Classifier: License :: OSI Approved :: MIT License
Classifier: Operating System :: POSIX :: Linux
Requires-Python: >=3.6
Requires-Dist: numpy
Requires-Dist: gitpython
Requires-Dist: sacremoses
Requires-Dist: sacrebleu
Requires-Dist: gitdir
Requires-Dist: jiwer
Requires-Dist: filelock
Requires-Dist: pytest
